{
    "$schema": "http://json-schema.org/schema#",
    "title": "company.serviceoffering.details",
    "version": "V0.01",
    "data_format": "json",
    "type": "object",
    "properties": {
      "Primary Service": {
        "type": "object",
        "description": "Services Offered by the Company",
        "enum": [
          "Architecture",
          "Interior Design",
          "Urban Planning",
          "Structual Engineering",
          "Building Services Engineering",
          "Civil Engineering",
          "Geotechnical Engineering",
          "Construction Managment"
      ]
      },
      "Service2": {
        "type": "object",
        "description": "Services Offered by the Company",
        "enum": [
          "Architecture",
          "Interior Design",
          "Urban Planning",
          "Structual Engineering",
          "Building Services Engineering",
          "Civil Engineering",
          "Geotechnical Engineering",
          "Construction Managment"
      ]
      },
      "Service3": {
        "type": "object",
        "description": "Services Offered by the Company",
        "enum": [
          "Architecture",
          "Interior Design",
          "Urban Planning",
          "Structual Engineering",
          "Building Services Engineering",
          "Civil Engineering",
          "Geotechnical Engineering",
          "Construction Managment"
      ]
      }

}

}